flow_federate_cli/__init__.py
flow_federate_cli/flow_cli.py
flow_federate_cli/command/__init__.py
flow_federate_cli/command/task.py
flow_federate_cli/utils/__init__.py
flow_federate_cli/utils/base_utils.py
flow_federate_sdk/__init__.py
flow_federate_sdk/api/__init__.py
flow_federate_sdk/api/task.py
flow_federate_sdk/tests/__init__.py
flow_federate_sdk/tests/task_test.py
flow_federate_sdk/utils/__init__.py
flow_federate_sdk/utils/base_utils.py
flow_federate_sdk/utils/http_utils.py
flow_server_cli/__init__.py
flow_server_cli/flow_cli.py
flow_server_cli/command/__init__.py
flow_server_cli/command/task.py
flow_server_cli/command/template.py
flow_server_cli/utils/__init__.py
flow_server_cli/utils/base_utils.py
flow_server_sdk/__init__.py
flow_server_sdk/api/__init__.py
flow_server_sdk/api/task.py
flow_server_sdk/api/template.py
flow_server_sdk/tests/__init__.py
flow_server_sdk/tests/task_test.py
flow_server_sdk/tests/template_test.py
flow_server_sdk/utils/__init__.py
flow_server_sdk/utils/base_utils.py
flow_server_sdk/utils/http_utils.py
iflearner_flow_client-0.2.0.dist-info/METADATA
iflearner_flow_client-0.2.0.dist-info/WHEEL
iflearner_flow_client-0.2.0.dist-info/entry_points.txt
iflearner_flow_client-0.2.0.dist-info/top_level.txt
iflearner_flow_client-0.2.0.dist-info/RECORD
